chaincrafter/__init__.py
chaincrafter/catalogs.py
chaincrafter/chains.py
chaincrafter/experiments.py
chaincrafter/models.py
chaincrafter/prompts.py
chaincrafter-0.2.3.dist-info/LICENSE
chaincrafter-0.2.3.dist-info/METADATA
chaincrafter-0.2.3.dist-info/WHEEL
chaincrafter-0.2.3.dist-info/top_level.txt
chaincrafter-0.2.3.dist-info/RECORD
