Metadata-Version: 2.1
Name: chaincrafter
Version: 0.2.3
Summary: Seamless integration and composability for large language model apps.
Home-page: https://github.com/rudolfolah/chaincrafter
Author: Rudolf Olah
Author-email: Rudolf Olah <rudolf.olah.to@gmail.com>
Project-URL: Homepage, https://rudolfolah.github.io/chaincrafter/
Project-URL: Bug Tracker, https://github.com/rudolfolah/chaincrafter/issues
Project-URL: Repository, https://github.com/rudolfolah/chaincrafter
Keywords: machine learning,ai,openai,llama,ml,gpt-4,gpt-3.5
Classifier: Development Status :: 3 - Alpha
Classifier: Intended Audience :: Developers
Classifier: Programming Language :: Python :: 3
Classifier: License :: OSI Approved :: MIT License
Classifier: Operating System :: OS Independent
Classifier: Topic :: Other/Nonlisted Topic
Provides: chaincrafter
Requires-Python: >=3.8
License-File: LICENSE
Requires-Dist: pandas ==2.0.3
Requires-Dist: pyyaml ==6.0.1
